c2hunt/__init__.py
c2hunt/cli.py
c2hunt/main.py
c2hunt/analysis/__init__.py
c2hunt/analysis/apkinfo.py
c2hunt/analysis/exclude_package.py
c2hunt/analysis/opcode.py
c2hunt/c2cdetect/__init__.py
test/__init__.py
test/test_apkinfo.py
test/test_c2detect.py
c2hunt-0.0.8.dist-info/METADATA
c2hunt-0.0.8.dist-info/WHEEL
c2hunt-0.0.8.dist-info/entry_points.txt
c2hunt-0.0.8.dist-info/top_level.txt
c2hunt-0.0.8.dist-info/RECORD
