Metadata-Version: 2.4
Name: c2hunt
Version: 0.0.8
Summary: Hunting Potential C2 Commands in Android Malware via Smali String Comparison and Control Flow Analysis
Author: JunWei Song
Author-email: JunWei Song <junwei.song.info@email.com>
Requires-Python: >=3.10
Requires-Dist: click
Requires-Dist: loguru
Requires-Dist: androguard
Requires-Dist: prettytable
Dynamic: author
Dynamic: requires-python
